{
  "instance": "SYN_BASELINE_099",
  "method": "FI",
  "start_method": "multistart",
  "time_limit": 60.0,
  "cost": 9184.609,
  "is_feasible": true,
  "unmet": {},
  "overprod": {},
  "elapsed_sec": 60.0,
  "active": {
    "S28": [
      [
        "PAT_0026",
        0,
        0.0
      ],
      [
        "PAT_0026",
        0,
        2471.8833
      ],
      [
        "PAT_0120",
        0,
        4943.7666
      ]
    ],
    "S31": [
      [
        "PAT_0047",
        0,
        1524.9996
      ],
      [
        "PAT_0047",
        0,
        4144.1368
      ]
    ],
    "S11": [
      [
        "PAT_0076",
        0,
        1590.8306
      ],
      [
        "PAT_0076",
        0,
        4209.9678
      ]
    ],
    "S36": [
      [
        "PAT_0484",
        0,
        495.6057
      ],
      [
        "PAT_0482",
        0,
        3833.8225
      ]
    ],
    "S21": [
      [
        "PAT_0251",
        0,
        0.0
      ],
      [
        "PAT_0251",
        0,
        3256.4488
      ]
    ],
    "S37": [
      [
        "PAT_0619",
        1,
        1327.6909
      ],
      [
        "PAT_0619",
        1,
        4612.186299999999
      ]
    ],
    "S8": [
      [
        "PAT_0380",
        0,
        3102.7162
      ]
    ],
    "S13": [
      [
        "PAT_0542",
        0,
        2051.3235
      ],
      [
        "PAT_0542",
        0,
        5335.8189
      ]
    ],
    "S18": [
      [
        "PAT_0599",
        0,
        0.0
      ]
    ],
    "S24": [
      [
        "PAT_0528",
        0,
        0.0
      ],
      [
        "PAT_0157",
        0,
        4121.8081
      ]
    ],
    "S4": [
      [
        "PAT_0156",
        0,
        0.0
      ],
      [
        "PAT_0522",
        1,
        3256.4488
      ]
    ],
    "S20": [
      [
        "PAT_0137",
        0,
        0.0
      ],
      [
        "PAT_0521",
        0,
        3256.4488
      ]
    ],
    "S12": [
      [
        "PAT_0008",
        0,
        1350.6817
      ],
      [
        "PAT_0137",
        0,
        4658.8917
      ]
    ],
    "S16": [
      [
        "PAT_0028",
        0,
        0.0
      ],
      [
        "PAT_0522",
        0,
        3182.9309
      ]
    ],
    "S1": [
      [
        "PAT_0137",
        0,
        4451.1963
      ]
    ],
    "S3": [
      [
        "PAT_0236",
        0,
        3508.7362
      ]
    ]
  }
}