{
  "instance": "SYN_BASELINE_143",
  "method": "SA",
  "start_method": "greedy",
  "time_limit": 60.0,
  "cost": 8809.0092,
  "is_feasible": true,
  "unmet": {},
  "overprod": {},
  "elapsed_sec": 60.06,
  "active": {
    "S32": [
      [
        "PAT_0030",
        0,
        0.0
      ],
      [
        "PAT_0030",
        0,
        3494.9743
      ]
    ],
    "S44": [
      [
        "PAT_0410",
        0,
        689.8431
      ],
      [
        "PAT_0410",
        0,
        3739.4234
      ]
    ],
    "S48": [
      [
        "PAT_0905",
        0,
        0.0
      ],
      [
        "PAT_1213",
        0,
        3049.5803
      ]
    ],
    "S52": [
      [
        "PAT_0261",
        0,
        0.0
      ],
      [
        "PAT_0284",
        0,
        3049.5803
      ],
      [
        "PAT_1052",
        1,
        6099.1606
      ]
    ],
    "S23": [
      [
        "PAT_1806",
        0,
        0.0
      ],
      [
        "PAT_1292",
        0,
        3800.2321
      ]
    ],
    "S33": [
      [
        "PAT_0387",
        0,
        0.0
      ],
      [
        "PAT_0397",
        1,
        3049.5803
      ]
    ],
    "S3": [
      [
        "PAT_1328",
        0,
        0.0
      ],
      [
        "PAT_0170",
        0,
        3179.0259000000005
      ]
    ],
    "S25": [
      [
        "PAT_0726",
        0,
        2249.6508
      ],
      [
        "PAT_0362",
        0,
        5299.2311
      ]
    ],
    "S47": [
      [
        "PAT_0151",
        0,
        1264.0204
      ],
      [
        "PAT_0151",
        0,
        4758.9947
      ]
    ],
    "S17": [
      [
        "PAT_0807",
        0,
        0.0
      ],
      [
        "PAT_0651",
        0,
        3049.5803
      ],
      [
        "PAT_1217",
        1,
        6222.0677
      ]
    ],
    "S14": [
      [
        "PAT_0064",
        0,
        0.0
      ],
      [
        "PAT_1806",
        0,
        3494.9743
      ]
    ],
    "S20": [
      [
        "PAT_1539",
        0,
        935.2213
      ],
      [
        "PAT_1809",
        0,
        5097.5523
      ]
    ],
    "S6": [
      [
        "PAT_0520",
        0,
        0.0
      ],
      [
        "PAT_1230",
        0,
        3049.5803
      ]
    ]
  }
}