{
  "instance": "SYN_SWEEP5_SIZE_XL_028",
  "method": "VNS_SA",
  "start_method": "greedy",
  "time_limit": 60.0,
  "cost": 32534.0236,
  "is_feasible": true,
  "unmet": {},
  "overprod": {
    "P5": 1,
    "P6": 4,
    "P8": 2,
    "P9": 3,
    "P15": 1,
    "P22": 1,
    "P26": 1,
    "P33": 2
  },
  "elapsed_sec": 60.41,
  "active": {
    "S38": [
      [
        "PAT_0166",
        0,
        0.0
      ],
      [
        "PAT_0166",
        0,
        1746.1883
      ],
      [
        "PAT_0166",
        0,
        3492.3766
      ],
      [
        "PAT_0166",
        0,
        5238.5649
      ]
    ],
    "S11": [
      [
        "PAT_6322",
        0,
        0.0
      ],
      [
        "PAT_6322",
        0,
        2218.8809
      ],
      [
        "PAT_6322",
        0,
        4437.7618
      ]
    ],
    "S80": [
      [
        "PAT_6789",
        0,
        0.0
      ],
      [
        "PAT_0188",
        0,
        2854.2295
      ]
    ],
    "S101": [
      [
        "PAT_4876",
        0,
        0.0
      ],
      [
        "PAT_4876",
        0,
        2567.3993
      ],
      [
        "PAT_4876",
        0,
        5134.7986
      ]
    ],
    "S58": [
      [
        "PAT_6671",
        0,
        0.0
      ],
      [
        "PAT_6671",
        0,
        2706.1113
      ],
      [
        "PAT_6671",
        0,
        5412.2226
      ]
    ],
    "S144": [
      [
        "PAT_6757",
        0,
        0.0
      ],
      [
        "PAT_6757",
        0,
        2706.1113
      ],
      [
        "PAT_6406",
        0,
        5412.2226
      ]
    ],
    "S97": [
      [
        "PAT_2889",
        0,
        0.0
      ],
      [
        "PAT_4375",
        0,
        3069.2984
      ]
    ],
    "S123": [
      [
        "PAT_6820",
        0,
        0.0
      ],
      [
        "PAT_6820",
        0,
        2854.2295
      ],
      [
        "PAT_6420",
        0,
        5708.459
      ]
    ],
    "S54": [
      [
        "PAT_0320",
        0,
        0.0
      ],
      [
        "PAT_6212",
        0,
        2903.0729
      ],
      [
        "PAT_6212",
        0,
        5121.9538
      ]
    ],
    "S29": [
      [
        "PAT_5225",
        0,
        0.0
      ],
      [
        "PAT_5225",
        0,
        2226.5864
      ],
      [
        "PAT_5225",
        0,
        4453.1728
      ]
    ],
    "S84": [
      [
        "PAT_5009",
        0,
        0.0
      ],
      [
        "PAT_5009",
        0,
        2226.5864
      ],
      [
        "PAT_5009",
        0,
        4453.1728
      ]
    ],
    "S41": [
      [
        "PAT_6962",
        0,
        0.0
      ],
      [
        "PAT_6962",
        0,
        2854.2295
      ]
    ],
    "S99": [
      [
        "PAT_4708",
        0,
        0.0
      ],
      [
        "PAT_4708",
        0,
        2567.3993
      ],
      [
        "PAT_6034",
        0,
        5134.7986
      ]
    ],
    "S147": [
      [
        "PAT_0334",
        0,
        0.0
      ],
      [
        "PAT_6434",
        0,
        2980.7733
      ]
    ],
    "S87": [
      [
        "PAT_6002",
        0,
        1310.39
      ],
      [
        "PAT_6002",
        0,
        3529.2709000000004
      ]
    ],
    "S119": [
      [
        "PAT_4669",
        0,
        0.0
      ],
      [
        "PAT_4669",
        0,
        2567.3993
      ],
      [
        "PAT_4669",
        0,
        5134.7986
      ]
    ],
    "S57": [
      [
        "PAT_4749",
        0,
        0.0
      ],
      [
        "PAT_4749",
        0,
        2567.3993
      ]
    ],
    "S94": [
      [
        "PAT_6801",
        0,
        971.9244
      ],
      [
        "PAT_6801",
        0,
        3826.1539
      ]
    ],
    "S121": [
      [
        "PAT_6017",
        0,
        0.0
      ],
      [
        "PAT_6017",
        0,
        2218.8809
      ],
      [
        "PAT_4760",
        0,
        4437.7618
      ]
    ],
    "S26": [
      [
        "PAT_4361",
        0,
        0.0
      ],
      [
        "PAT_4919",
        0,
        4944.7437
      ]
    ],
    "S27": [
      [
        "PAT_4890",
        0,
        0.0
      ],
      [
        "PAT_4890",
        0,
        2226.5864
      ],
      [
        "PAT_5218",
        0,
        4453.1728
      ]
    ],
    "S75": [
      [
        "PAT_6254",
        0,
        0.0
      ],
      [
        "PAT_6254",
        0,
        2218.8809
      ],
      [
        "PAT_6254",
        0,
        4437.7618
      ]
    ],
    "S118": [
      [
        "PAT_4665",
        0,
        0.0
      ],
      [
        "PAT_4665",
        0,
        2567.3993
      ],
      [
        "PAT_6742",
        1,
        5134.7986
      ]
    ],
    "S43": [
      [
        "PAT_4379",
        0,
        0.0
      ]
    ],
    "S125": [
      [
        "PAT_6445",
        0,
        0.0
      ],
      [
        "PAT_6445",
        0,
        2706.1113
      ]
    ],
    "S6": [
      [
        "PAT_4379",
        0,
        0.0
      ],
      [
        "PAT_0322",
        0,
        4944.7437
      ]
    ],
    "S142": [
      [
        "PAT_6445",
        0,
        0.0
      ],
      [
        "PAT_6445",
        0,
        2706.1113
      ]
    ],
    "S140": [
      [
        "PAT_4379",
        0,
        1188.8435
      ]
    ],
    "S91": [
      [
        "PAT_4378",
        0,
        1543.7762
      ]
    ],
    "S98": [
      [
        "PAT_6016",
        0,
        0.0
      ],
      [
        "PAT_6799",
        0,
        3118.5515
      ]
    ],
    "S33": [
      [
        "PAT_6445",
        0,
        2333.9873
      ]
    ],
    "S122": [
      [
        "PAT_4383",
        0,
        0.0
      ]
    ],
    "S53": [
      [
        "PAT_4383",
        0,
        2717.9491
      ]
    ],
    "S108": [
      [
        "PAT_4918",
        0,
        3720.9471000000003
      ]
    ],
    "S135": [
      [
        "PAT_4382",
        0,
        0.0
      ]
    ],
    "S17": [
      [
        "PAT_4382",
        0,
        1358.7538
      ]
    ],
    "S68": [
      [
        "PAT_4382",
        0,
        1148.963
      ]
    ],
    "S106": [
      [
        "PAT_4382",
        0,
        0.0
      ]
    ],
    "S141": [
      [
        "PAT_4382",
        0,
        2785.45
      ]
    ],
    "S117": [
      [
        "PAT_4440",
        0,
        0.0
      ]
    ],
    "S62": [
      [
        "PAT_4382",
        0,
        2852.9246
      ]
    ],
    "S86": [
      [
        "PAT_4382",
        0,
        0.0
      ]
    ],
    "S132": [
      [
        "PAT_4583",
        0,
        0.0
      ]
    ],
    "S55": [
      [
        "PAT_4440",
        0,
        0.0
      ]
    ],
    "S59": [
      [
        "PAT_5677",
        0,
        0.0
      ],
      [
        "PAT_5677",
        0,
        2226.5864
      ],
      [
        "PAT_5677",
        0,
        4453.1728
      ]
    ],
    "S113": [
      [
        "PAT_3412",
        0,
        0.0
      ],
      [
        "PAT_3412",
        0,
        2642.7612
      ],
      [
        "PAT_5964",
        0,
        5285.5224
      ]
    ],
    "S30": [
      [
        "PAT_3190",
        0,
        0.0
      ],
      [
        "PAT_3190",
        0,
        2642.7612
      ]
    ],
    "S126": [
      [
        "PAT_3552",
        0,
        795.8899
      ],
      [
        "PAT_5706",
        1,
        3438.6511
      ]
    ],
    "S20": [
      [
        "PAT_2025",
        0,
        0.0
      ],
      [
        "PAT_2025",
        0,
        2642.7612
      ]
    ],
    "S90": [
      [
        "PAT_2190",
        0,
        0.0
      ],
      [
        "PAT_2190",
        0,
        2642.7612
      ],
      [
        "PAT_5958",
        0,
        5285.5224
      ]
    ],
    "S4": [
      [
        "PAT_1124",
        0,
        2888.718
      ]
    ],
    "S15": [
      [
        "PAT_0335",
        0,
        0.0
      ]
    ],
    "S133": [
      [
        "PAT_0335",
        0,
        0.0
      ]
    ],
    "S1": [
      [
        "PAT_0335",
        0,
        1006.9802
      ]
    ],
    "S9": [
      [
        "PAT_0335",
        0,
        0.0
      ]
    ],
    "S93": [
      [
        "PAT_4663",
        0,
        0.0
      ],
      [
        "PAT_0335",
        0,
        3183.8822
      ]
    ],
    "S44": [
      [
        "PAT_4503",
        0,
        0.0
      ]
    ]
  }
}