{
  "instance": "SYN_SWEEP5_SIZE_XL_013",
  "method": "VNS_SA",
  "start_method": "greedy",
  "time_limit": 60.0,
  "cost": 34102.3671,
  "is_feasible": true,
  "unmet": {},
  "overprod": {
    "P2": 2,
    "P23": 1
  },
  "elapsed_sec": 60.04,
  "active": {
    "S107": [
      [
        "PAT_0100",
        0,
        0.0
      ],
      [
        "PAT_0100",
        0,
        2546.8886
      ]
    ],
    "S133": [
      [
        "PAT_0007",
        0,
        0.0
      ],
      [
        "PAT_0007",
        0,
        2807.9764
      ]
    ],
    "S143": [
      [
        "PAT_0183",
        0,
        0.0
      ],
      [
        "PAT_0016",
        0,
        2596.9444
      ]
    ],
    "S7": [
      [
        "PAT_1282",
        0,
        0.0
      ],
      [
        "PAT_1345",
        0,
        3244.0123
      ]
    ],
    "S93": [
      [
        "PAT_0183",
        0,
        0.0
      ],
      [
        "PAT_1293",
        0,
        2653.5607999999997
      ]
    ],
    "S67": [
      [
        "PAT_0197",
        0,
        0.0
      ],
      [
        "PAT_0004",
        0,
        3066.9036
      ]
    ],
    "S65": [
      [
        "PAT_1364",
        0,
        1276.8112
      ]
    ],
    "S85": [
      [
        "PAT_1445",
        0,
        0.0
      ],
      [
        "PAT_0901",
        0,
        3671.6174
      ]
    ],
    "S124": [
      [
        "PAT_1376",
        0,
        0.0
      ],
      [
        "PAT_1375",
        0,
        3135.6794
      ]
    ],
    "S37": [
      [
        "PAT_1639",
        0,
        0.0
      ],
      [
        "PAT_1107",
        0,
        936.0697999999998
      ],
      [
        "PAT_0174",
        0,
        3196.6276999999995
      ]
    ],
    "S44": [
      [
        "PAT_1639",
        0,
        0.0
      ],
      [
        "PAT_0073",
        0,
        912.8926
      ],
      [
        "PAT_0073",
        0,
        3459.7812000000004
      ]
    ],
    "S27": [
      [
        "PAT_1198",
        0,
        0.0
      ],
      [
        "PAT_0823",
        0,
        2407.2485000000006
      ]
    ],
    "S58": [
      [
        "PAT_0891",
        0,
        0.0
      ],
      [
        "PAT_1286",
        1,
        2260.5579
      ]
    ],
    "S17": [
      [
        "PAT_1654",
        0,
        1279.136
      ]
    ],
    "S90": [
      [
        "PAT_0157",
        0,
        0.0
      ],
      [
        "PAT_0154",
        0,
        3341.7314
      ]
    ],
    "S86": [
      [
        "PAT_1451",
        0,
        0.0
      ],
      [
        "PAT_0183",
        0,
        3671.6174
      ]
    ],
    "S47": [
      [
        "PAT_0153",
        0,
        0.0
      ],
      [
        "PAT_0153",
        0,
        3341.7314
      ]
    ],
    "S137": [
      [
        "PAT_0017",
        0,
        0.0
      ],
      [
        "PAT_1638",
        0,
        2807.9764
      ],
      [
        "PAT_1639",
        1,
        3720.869
      ]
    ],
    "S22": [
      [
        "PAT_0153",
        0,
        1137.39
      ]
    ],
    "S122": [
      [
        "PAT_0180",
        0,
        0.0
      ],
      [
        "PAT_0180",
        0,
        2451.5803
      ]
    ],
    "S18": [
      [
        "PAT_1243",
        0,
        0.0
      ]
    ],
    "S12": [
      [
        "PAT_0159",
        0,
        0.0
      ]
    ],
    "S4": [
      [
        "PAT_0151",
        0,
        1610.766
      ]
    ],
    "S49": [
      [
        "PAT_1364",
        0,
        750.3323
      ]
    ],
    "S135": [
      [
        "PAT_1285",
        0,
        0.0
      ]
    ],
    "S57": [
      [
        "PAT_1364",
        0,
        2130.702
      ]
    ],
    "S71": [
      [
        "PAT_1501",
        0,
        0.0
      ]
    ],
    "S10": [
      [
        "PAT_1247",
        0,
        0.0
      ],
      [
        "PAT_0010",
        1,
        3079.4435
      ]
    ],
    "S21": [
      [
        "PAT_1412",
        0,
        0.0
      ]
    ],
    "S132": [
      [
        "PAT_1646",
        0,
        0.0
      ],
      [
        "PAT_1448",
        0,
        2046.4386
      ]
    ],
    "S26": [
      [
        "PAT_0008",
        0,
        0.0
      ]
    ],
    "S73": [
      [
        "PAT_1644",
        0,
        0.0
      ],
      [
        "PAT_1653",
        0,
        2070.085
      ]
    ],
    "S33": [
      [
        "PAT_0153",
        0,
        0.0
      ]
    ],
    "S138": [
      [
        "PAT_1445",
        0,
        1624.4083
      ]
    ],
    "S78": [
      [
        "PAT_1448",
        0,
        0.0
      ]
    ],
    "S148": [
      [
        "PAT_0816",
        0,
        0.0
      ],
      [
        "PAT_0198",
        2,
        2260.5579
      ]
    ],
    "S29": [
      [
        "PAT_1536",
        0,
        0.0
      ]
    ],
    "S28": [
      [
        "PAT_0035",
        0,
        2013.0165
      ]
    ],
    "S75": [
      [
        "PAT_1257",
        0,
        2307.7022
      ]
    ],
    "S92": [
      [
        "PAT_1310",
        0,
        0.0
      ],
      [
        "PAT_1039",
        1,
        4316.5646
      ]
    ],
    "S89": [
      [
        "PAT_1639",
        0,
        0.0
      ],
      [
        "PAT_0212",
        0,
        912.8926
      ]
    ],
    "S123": [
      [
        "PAT_1364",
        0,
        1665.1318
      ]
    ],
    "S19": [
      [
        "PAT_1282",
        0,
        824.286
      ]
    ],
    "S6": [
      [
        "PAT_1252",
        0,
        0.0
      ]
    ],
    "S94": [
      [
        "PAT_0197",
        0,
        0.0
      ],
      [
        "PAT_1386",
        0,
        2652.6268
      ]
    ],
    "S45": [
      [
        "PAT_1272",
        0,
        0.0
      ],
      [
        "PAT_0119",
        0,
        3079.4435
      ]
    ],
    "S98": [
      [
        "PAT_1371",
        0,
        0.0
      ],
      [
        "PAT_1371",
        0,
        3135.6794
      ]
    ],
    "S25": [
      [
        "PAT_0153",
        0,
        0.0
      ]
    ],
    "S128": [
      [
        "PAT_1281",
        0,
        0.0
      ]
    ],
    "S114": [
      [
        "PAT_1304",
        0,
        608.4017
      ]
    ],
    "S39": [
      [
        "PAT_1448",
        0,
        0.0
      ]
    ],
    "S51": [
      [
        "PAT_0153",
        0,
        0.0
      ],
      [
        "PAT_0251",
        0,
        3341.7314
      ]
    ],
    "S115": [
      [
        "PAT_1461",
        0,
        0.0
      ]
    ],
    "S76": [
      [
        "PAT_1364",
        0,
        1117.3835
      ]
    ],
    "S129": [
      [
        "PAT_0183",
        0,
        2465.3697
      ]
    ],
    "S46": [
      [
        "PAT_1461",
        0,
        0.0
      ]
    ],
    "S64": [
      [
        "PAT_1384",
        0,
        0.0
      ]
    ],
    "S35": [
      [
        "PAT_1348",
        0,
        0.0
      ],
      [
        "PAT_1257",
        0,
        3079.4435
      ]
    ],
    "S109": [
      [
        "PAT_0113",
        0,
        0.0
      ],
      [
        "PAT_0113",
        0,
        2546.8886
      ]
    ],
    "S66": [
      [
        "PAT_1500",
        0,
        973.799
      ]
    ],
    "S95": [
      [
        "PAT_1364",
        0,
        0.0
      ],
      [
        "PAT_1650",
        0,
        3135.6794
      ]
    ],
    "S103": [
      [
        "PAT_1653",
        0,
        1745.3653
      ]
    ],
    "S81": [
      [
        "PAT_1445",
        1,
        955.1919
      ]
    ],
    "S136": [
      [
        "PAT_1448",
        0,
        0.0
      ]
    ],
    "S40": [
      [
        "PAT_1500",
        0,
        0.0
      ]
    ]
  }
}