{
  "instance": "SYN_SWEEP1_DEFECT_LOW_012",
  "method": "TS",
  "start_method": "multistart",
  "time_limit": 60.0,
  "cost": 8540.5716,
  "is_feasible": true,
  "unmet": {},
  "overprod": {
    "P7": 3,
    "P8": 1
  },
  "elapsed_sec": 60.01,
  "active": {
    "S15": [
      [
        "PAT_0541",
        0,
        0.0
      ],
      [
        "PAT_0572",
        0,
        3103.853
      ]
    ],
    "S3": [
      [
        "PAT_1047",
        0,
        0.0
      ],
      [
        "PAT_1047",
        0,
        3510.2821
      ]
    ],
    "S24": [
      [
        "PAT_0053",
        0,
        826.3219
      ],
      [
        "PAT_0736",
        0,
        4296.072899999999
      ]
    ],
    "S27": [
      [
        "PAT_0602",
        0,
        0.0
      ],
      [
        "PAT_0974",
        0,
        3510.1179
      ]
    ],
    "S18": [
      [
        "PAT_0610",
        0,
        0.0
      ],
      [
        "PAT_0584",
        1,
        5670.5712
      ]
    ],
    "S29": [
      [
        "PAT_0581",
        0,
        854.6593
      ],
      [
        "PAT_0586",
        0,
        4364.7772
      ]
    ],
    "S14": [
      [
        "PAT_0044",
        0,
        0.0
      ],
      [
        "PAT_0044",
        0,
        3083.0945
      ]
    ],
    "S33": [
      [
        "PAT_1121",
        0,
        0.0
      ],
      [
        "PAT_1121",
        0,
        3510.2821
      ]
    ],
    "S36": [
      [
        "PAT_0545",
        0,
        0.0
      ],
      [
        "PAT_0095",
        0,
        2564.5573000000004
      ],
      [
        "PAT_0095",
        0,
        5647.651800000001
      ]
    ],
    "S22": [
      [
        "PAT_0578",
        0,
        0.0
      ],
      [
        "PAT_0595",
        1,
        4167.0293
      ]
    ],
    "S30": [
      [
        "PAT_0580",
        0,
        0.0
      ],
      [
        "PAT_0561",
        0,
        5134.632299999999
      ],
      [
        "PAT_0561",
        0,
        7626.0857
      ]
    ],
    "S12": [
      [
        "PAT_0209",
        0,
        0.0
      ],
      [
        "PAT_0629",
        0,
        3745.0268
      ]
    ],
    "S38": [
      [
        "PAT_1121",
        0,
        0.0
      ],
      [
        "PAT_1121",
        0,
        3510.2821
      ]
    ]
  }
}