{
  "instance": "SYN_BASELINE_070",
  "method": "VNS_SA",
  "start_method": "multistart",
  "time_limit": 60.0,
  "cost": 7006.031,
  "is_feasible": true,
  "unmet": {},
  "overprod": {},
  "elapsed_sec": 11.11,
  "active": {
    "S7": [
      [
        "PAT_0112",
        0,
        0.0
      ],
      [
        "PAT_0077",
        0,
        2715.5515
      ]
    ],
    "S39": [
      [
        "PAT_0112",
        0,
        0.0
      ],
      [
        "PAT_0107",
        0,
        3722.5086
      ]
    ],
    "S28": [
      [
        "PAT_0101",
        0,
        0.0
      ],
      [
        "PAT_0102",
        0,
        4304.169
      ]
    ],
    "S10": [
      [
        "PAT_0016",
        0,
        0.0
      ],
      [
        "PAT_0119",
        0,
        3132.1596
      ]
    ],
    "S24": [
      [
        "PAT_0017",
        0,
        0.0
      ],
      [
        "PAT_0112",
        0,
        2245.0605
      ],
      [
        "PAT_0129",
        0,
        4960.612
      ]
    ],
    "S5": [
      [
        "PAT_0135",
        0,
        0.0
      ],
      [
        "PAT_0125",
        0,
        2439.2914
      ],
      [
        "PAT_0084",
        1,
        5157.5749
      ]
    ],
    "S4": [
      [
        "PAT_0135",
        0,
        0.0
      ],
      [
        "PAT_0103",
        0,
        2439.2914
      ]
    ],
    "S37": [
      [
        "PAT_0107",
        0,
        958.081
      ],
      [
        "PAT_0010",
        1,
        6060.3958
      ]
    ],
    "S14": [
      [
        "PAT_0107",
        0,
        0.0
      ],
      [
        "PAT_0107",
        0,
        4037.0516
      ]
    ],
    "S11": [
      [
        "PAT_0014",
        0,
        0.0
      ],
      [
        "PAT_0018",
        0,
        2245.0605
      ]
    ]
  }
}