{
  "instance": "SYN_BASELINE_060",
  "method": "VNS_SA",
  "start_method": "multistart",
  "time_limit": 60.0,
  "cost": 6859.0351,
  "is_feasible": true,
  "unmet": {},
  "overprod": {
    "P4": 1,
    "P11": 2
  },
  "elapsed_sec": 16.86,
  "active": {
    "S6": [
      [
        "PAT_0820",
        0,
        0.0
      ],
      [
        "PAT_0667",
        0,
        2428.4511999999995
      ],
      [
        "PAT_0153",
        0,
        4636.3126999999995
      ]
    ],
    "S38": [
      [
        "PAT_0883",
        0,
        0.0
      ],
      [
        "PAT_0295",
        0,
        3979.4983999999995
      ]
    ],
    "S17": [
      [
        "PAT_0007",
        0,
        0.0
      ],
      [
        "PAT_0119",
        0,
        2839.8336
      ]
    ],
    "S32": [
      [
        "PAT_0455",
        0,
        1137.2148
      ],
      [
        "PAT_0378",
        0,
        3345.0762999999997
      ],
      [
        "PAT_0028",
        0,
        5552.9378
      ]
    ],
    "S13": [
      [
        "PAT_0298",
        0,
        0.0
      ],
      [
        "PAT_0045",
        1,
        4626.9268
      ]
    ],
    "S29": [
      [
        "PAT_0014",
        0,
        1966.1774
      ],
      [
        "PAT_0887",
        0,
        4806.011
      ]
    ],
    "S37": [
      [
        "PAT_0524",
        0,
        0.0
      ],
      [
        "PAT_0019",
        0,
        3880.5136
      ]
    ],
    "S16": [
      [
        "PAT_0164",
        0,
        3780.9171
      ]
    ],
    "S8": [
      [
        "PAT_0132",
        1,
        1158.4285
      ],
      [
        "PAT_0045",
        0,
        5785.3553
      ]
    ],
    "S18": [
      [
        "PAT_0042",
        0,
        0.0
      ],
      [
        "PAT_0048",
        0,
        2839.8336
      ]
    ]
  }
}