{
  "instance": "SYN_BASELINE_058",
  "method": "VNS_SA",
  "start_method": "greedy",
  "time_limit": 60.0,
  "cost": 8038.0533,
  "is_feasible": true,
  "unmet": {},
  "overprod": {},
  "elapsed_sec": 10.0,
  "active": {
    "S4": [
      [
        "PAT_0002",
        0,
        0.0
      ]
    ],
    "S27": [
      [
        "PAT_0002",
        0,
        0.0
      ],
      [
        "PAT_0001",
        0,
        3950.4529
      ]
    ],
    "S31": [
      [
        "PAT_0009",
        0,
        0.0
      ]
    ],
    "S35": [
      [
        "PAT_0856",
        0,
        2976.6896
      ]
    ],
    "S28": [
      [
        "PAT_0004",
        0,
        0.0
      ],
      [
        "PAT_0168",
        0,
        4049.2534
      ]
    ],
    "S6": [
      [
        "PAT_0775",
        0,
        0.0
      ],
      [
        "PAT_0002",
        0,
        3634.8969
      ]
    ],
    "S7": [
      [
        "PAT_0167",
        0,
        0.0
      ]
    ],
    "S21": [
      [
        "PAT_0757",
        0,
        0.0
      ],
      [
        "PAT_0012",
        0,
        3216.0374
      ]
    ],
    "S17": [
      [
        "PAT_0005",
        0,
        1502.7261
      ]
    ],
    "S11": [
      [
        "PAT_0799",
        0,
        0.0
      ],
      [
        "PAT_0799",
        0,
        2551.1626
      ]
    ],
    "S25": [
      [
        "PAT_0226",
        0,
        536.5196
      ]
    ],
    "S34": [
      [
        "PAT_0084",
        0,
        999.5146
      ],
      [
        "PAT_0109",
        0,
        4251.2444
      ]
    ],
    "S9": [
      [
        "PAT_0704",
        0,
        0.0
      ],
      [
        "PAT_0011",
        0,
        3251.7298
      ]
    ],
    "S10": [
      [
        "PAT_0216",
        0,
        983.3605
      ]
    ],
    "S26": [
      [
        "PAT_0277",
        0,
        0.0
      ],
      [
        "PAT_0856",
        0,
        3251.7298
      ]
    ]
  }
}