{
  "instance": "SYN_BASELINE_050",
  "method": "SA",
  "start_method": "multistart",
  "time_limit": 60.0,
  "cost": 11511.8019,
  "is_feasible": true,
  "unmet": {},
  "overprod": {
    "P4": 1,
    "P8": 2,
    "P11": 1
  },
  "elapsed_sec": 60.1,
  "active": {
    "S11": [
      [
        "PAT_0084",
        0,
        0.0
      ]
    ],
    "S26": [
      [
        "PAT_0084",
        0,
        632.2759
      ]
    ],
    "S52": [
      [
        "PAT_0084",
        0,
        0.0
      ]
    ],
    "S7": [
      [
        "PAT_0084",
        0,
        0.0
      ]
    ],
    "S15": [
      [
        "PAT_0084",
        0,
        0.0
      ]
    ],
    "S31": [
      [
        "PAT_4524",
        0,
        0.0
      ],
      [
        "PAT_2430",
        0,
        1563.039
      ],
      [
        "PAT_5116",
        0,
        3516.7984
      ]
    ],
    "S40": [
      [
        "PAT_0093",
        0,
        0.0
      ]
    ],
    "S29": [
      [
        "PAT_5130",
        0,
        0.0
      ],
      [
        "PAT_0013",
        0,
        2460.5064
      ]
    ],
    "S41": [
      [
        "PAT_1446",
        0,
        0.0
      ],
      [
        "PAT_5172",
        1,
        1563.039
      ],
      [
        "PAT_0077",
        2,
        4023.5454
      ]
    ],
    "S8": [
      [
        "PAT_5218",
        0,
        0.0
      ],
      [
        "PAT_0013",
        1,
        2460.5064
      ]
    ],
    "S19": [
      [
        "PAT_0039",
        0,
        0.0
      ],
      [
        "PAT_0084",
        0,
        1755.4515
      ]
    ],
    "S34": [
      [
        "PAT_5099",
        0,
        0.0
      ]
    ],
    "S1": [
      [
        "PAT_5222",
        0,
        0.0
      ]
    ],
    "S17": [
      [
        "PAT_0345",
        0,
        0.0
      ],
      [
        "PAT_5171",
        0,
        1563.039
      ]
    ],
    "S50": [
      [
        "PAT_5259",
        0,
        0.0
      ],
      [
        "PAT_5196",
        0,
        2460.5064
      ]
    ],
    "S21": [
      [
        "PAT_5153",
        0,
        0.0
      ],
      [
        "PAT_5166",
        1,
        3309.0513
      ]
    ],
    "S42": [
      [
        "PAT_5199",
        0,
        0.0
      ],
      [
        "PAT_5222",
        0,
        3153.4431
      ]
    ],
    "S47": [
      [
        "PAT_5136",
        0,
        673.3208
      ]
    ],
    "S28": [
      [
        "PAT_0558",
        0,
        0.0
      ],
      [
        "PAT_0055",
        0,
        1563.039
      ],
      [
        "PAT_0055",
        0,
        3318.4905
      ]
    ],
    "S44": [
      [
        "PAT_4989",
        0,
        0.0
      ],
      [
        "PAT_5159",
        0,
        1563.039
      ]
    ],
    "S25": [
      [
        "PAT_0072",
        0,
        0.0
      ],
      [
        "PAT_0039",
        1,
        3752.055
      ]
    ]
  }
}