{
  "instance": "SYN_SWEEP4_WIDRATIO_HIGH_002",
  "method": "SA",
  "start_method": "greedy",
  "time_limit": 60.0,
  "cost": 10686.1221,
  "is_feasible": true,
  "unmet": {},
  "overprod": {
    "P2": 2
  },
  "elapsed_sec": 60.03,
  "active": {
    "S32": [
      [
        "PAT_0079",
        0,
        2267.2564999999995
      ],
      [
        "PAT_0079",
        0,
        4130.6302
      ],
      [
        "PAT_0079",
        0,
        5994.0039
      ]
    ],
    "S7": [
      [
        "PAT_0032",
        0,
        1486.6943
      ],
      [
        "PAT_0064",
        0,
        3350.068
      ],
      [
        "PAT_0064",
        0,
        5213.4417
      ]
    ],
    "S45": [
      [
        "PAT_0476",
        0,
        0.0
      ],
      [
        "PAT_0057",
        1,
        3998.9113
      ],
      [
        "PAT_0037",
        1,
        5862.285
      ]
    ],
    "S20": [
      [
        "PAT_0447",
        0,
        0.0
      ],
      [
        "PAT_0447",
        0,
        3271.1727
      ]
    ],
    "S16": [
      [
        "PAT_0484",
        0,
        0.0
      ],
      [
        "PAT_0457",
        0,
        3526.5446
      ]
    ],
    "S54": [
      [
        "PAT_0105",
        0,
        0.0
      ],
      [
        "PAT_0249",
        0,
        1863.3737
      ],
      [
        "PAT_0061",
        1,
        5406.887500000001
      ]
    ],
    "S3": [
      [
        "PAT_0205",
        0,
        0.0
      ],
      [
        "PAT_0515",
        0,
        3543.5138
      ]
    ],
    "S26": [
      [
        "PAT_0202",
        0,
        0.0
      ],
      [
        "PAT_0518",
        0,
        3543.5138
      ]
    ],
    "S37": [
      [
        "PAT_0329",
        0,
        0.0
      ],
      [
        "PAT_0441",
        0,
        3543.5138
      ]
    ],
    "S30": [
      [
        "PAT_0530",
        0,
        0.0
      ],
      [
        "PAT_0087",
        0,
        3271.1727
      ],
      [
        "PAT_0087",
        0,
        5134.5464
      ]
    ],
    "S27": [
      [
        "PAT_0557",
        0,
        0.0
      ],
      [
        "PAT_0454",
        0,
        3271.1727
      ]
    ],
    "S19": [
      [
        "PAT_0120",
        0,
        0.0
      ],
      [
        "PAT_0120",
        0,
        1863.3737
      ],
      [
        "PAT_0102",
        1,
        3858.532
      ]
    ],
    "S47": [
      [
        "PAT_0136",
        0,
        0.0
      ],
      [
        "PAT_0066",
        1,
        4020.5233
      ]
    ],
    "S43": [
      [
        "PAT_0326",
        0,
        798.5078
      ],
      [
        "PAT_0057",
        0,
        4342.0216
      ]
    ],
    "S9": [
      [
        "PAT_0024",
        0,
        847.5599
      ],
      [
        "PAT_0201",
        1,
        2710.9336000000003
      ]
    ]
  }
}