{
  "instance": "SYN_SWEEP4_WIDRATIO_LOW_027",
  "method": "GRASP_SA",
  "start_method": "none",
  "time_limit": 60.0,
  "cost": 11725.1266,
  "is_feasible": true,
  "unmet": {},
  "overprod": {},
  "elapsed_sec": 60.01,
  "active": {
    "S2": [
      [
        "PAT_0052",
        0,
        2270.2957
      ],
      [
        "PAT_0052",
        0,
        4127.7709
      ]
    ],
    "S13": [
      [
        "PAT_0005",
        0,
        1516.4098
      ],
      [
        "PAT_0013",
        0,
        4706.4364000000005
      ],
      [
        "PAT_0013",
        0,
        6146.8689
      ]
    ],
    "S50": [
      [
        "PAT_0008",
        0,
        0.0
      ]
    ],
    "S23": [
      [
        "PAT_0003",
        0,
        0.0
      ],
      [
        "PAT_0012",
        0,
        3550.0872
      ]
    ],
    "S4": [
      [
        "PAT_0001",
        0,
        0.0
      ],
      [
        "PAT_0008",
        0,
        4076.5428
      ]
    ],
    "S41": [
      [
        "PAT_0023",
        0,
        0.0
      ],
      [
        "PAT_0015",
        1,
        4265.136
      ]
    ],
    "S21": [
      [
        "PAT_0023",
        0,
        1359.1437
      ]
    ],
    "S45": [
      [
        "PAT_0021",
        0,
        0.0
      ],
      [
        "PAT_0004",
        0,
        3611.2042
      ]
    ],
    "S31": [
      [
        "PAT_0009",
        0,
        0.0
      ],
      [
        "PAT_0021",
        0,
        3154.3938
      ]
    ],
    "S26": [
      [
        "PAT_0018",
        0,
        0.0
      ],
      [
        "PAT_0013",
        0,
        1626.5499
      ],
      [
        "PAT_0003",
        0,
        3874.4035000000003
      ]
    ],
    "S25": [
      [
        "PAT_0023",
        0,
        1614.2837
      ]
    ],
    "S9": [
      [
        "PAT_0018",
        0,
        356.8703
      ],
      [
        "PAT_0005",
        0,
        2483.0827
      ]
    ],
    "S28": [
      [
        "PAT_0020",
        0,
        1795.282
      ],
      [
        "PAT_0024",
        0,
        3235.7145
      ]
    ],
    "S49": [
      [
        "PAT_0023",
        0,
        2662.2643
      ]
    ],
    "S7": [
      [
        "PAT_0021",
        0,
        0.0
      ]
    ],
    "S48": [
      [
        "PAT_0008",
        0,
        0.0
      ],
      [
        "PAT_0009",
        0,
        3154.3938
      ]
    ],
    "S16": [
      [
        "PAT_0005",
        0,
        0.0
      ]
    ],
    "S24": [
      [
        "PAT_0021",
        0,
        1946.033
      ]
    ],
    "S30": [
      [
        "PAT_0021",
        0,
        574.9178
      ]
    ],
    "S43": [
      [
        "PAT_0021",
        1,
        1850.7218
      ]
    ],
    "S46": [
      [
        "PAT_0037",
        0,
        1148.624
      ],
      [
        "PAT_0016",
        2,
        4749.415
      ]
    ],
    "S29": [
      [
        "PAT_0021",
        0,
        1408.2509
      ]
    ],
    "S19": [
      [
        "PAT_0021",
        0,
        2759.6079
      ]
    ],
    "S10": [
      [
        "PAT_0021",
        0,
        1008.5549
      ]
    ]
  }
}