{
  "instance": "SYN_SWEEP4_WIDRATIO_HIGH_010",
  "method": "VNS_SA",
  "start_method": "greedy",
  "time_limit": 60.0,
  "cost": 9593.6242,
  "is_feasible": true,
  "unmet": {},
  "overprod": {
    "P1": 1,
    "P8": 1,
    "P9": 3,
    "P10": 1
  },
  "elapsed_sec": 10.88,
  "active": {
    "S23": [
      [
        "PAT_0289",
        0,
        0.0
      ],
      [
        "PAT_0289",
        0,
        1410.5057
      ],
      [
        "PAT_0289",
        0,
        2821.0114
      ],
      [
        "PAT_0289",
        0,
        4231.5171
      ]
    ],
    "S18": [
      [
        "PAT_0275",
        0,
        0.0
      ],
      [
        "PAT_0275",
        0,
        1818.9344
      ],
      [
        "PAT_0275",
        0,
        3637.8688
      ]
    ],
    "S33": [
      [
        "PAT_0279",
        0,
        0.0
      ],
      [
        "PAT_0279",
        0,
        1410.5057
      ],
      [
        "PAT_0279",
        0,
        2821.0114
      ]
    ],
    "S45": [
      [
        "PAT_0062",
        0,
        0.0
      ],
      [
        "PAT_0062",
        0,
        2979.858
      ]
    ],
    "S46": [
      [
        "PAT_0253",
        0,
        0.0
      ],
      [
        "PAT_0253",
        0,
        3133.7998
      ]
    ],
    "S31": [
      [
        "PAT_0053",
        0,
        1633.6156
      ],
      [
        "PAT_0053",
        0,
        4613.4736
      ]
    ],
    "S48": [
      [
        "PAT_0193",
        0,
        0.0
      ],
      [
        "PAT_0193",
        0,
        3133.7998
      ]
    ],
    "S44": [
      [
        "PAT_0078",
        0,
        0.0
      ],
      [
        "PAT_0078",
        0,
        3133.7998
      ]
    ],
    "S24": [
      [
        "PAT_0174",
        0,
        0.0
      ],
      [
        "PAT_0174",
        0,
        3133.7998
      ],
      [
        "PAT_0278",
        0,
        6267.5996
      ]
    ],
    "S13": [
      [
        "PAT_0182",
        0,
        0.0
      ],
      [
        "PAT_0182",
        0,
        3133.7998
      ]
    ],
    "S26": [
      [
        "PAT_0176",
        0,
        0.0
      ]
    ],
    "S6": [
      [
        "PAT_0041",
        0,
        0.0
      ],
      [
        "PAT_0041",
        0,
        2979.858
      ]
    ],
    "S36": [
      [
        "PAT_0035",
        0,
        0.0
      ],
      [
        "PAT_0035",
        0,
        2979.858
      ]
    ],
    "S12": [
      [
        "PAT_0008",
        0,
        0.0
      ],
      [
        "PAT_0008",
        0,
        2979.858
      ]
    ],
    "S32": [
      [
        "PAT_0146",
        0,
        0.0
      ],
      [
        "PAT_0009",
        0,
        3762.6897
      ]
    ]
  }
}