{
  "instance": "SYN_SWEEP4_WIDRATIO_LOW_003",
  "method": "GRASP_SA",
  "start_method": "none",
  "time_limit": 60.0,
  "cost": 10572.5554,
  "is_feasible": false,
  "unmet": {
    "P3": 4,
    "P7": 4
  },
  "overprod": {
    "P1": 1,
    "P13": 2,
    "P14": 4
  },
  "elapsed_sec": 38.66,
  "active": {
    "S30": [
      [
        "PAT_0186",
        0,
        1309.3087
      ]
    ],
    "S42": [
      [
        "PAT_0138",
        0,
        0.0
      ],
      [
        "PAT_0138",
        0,
        2442.2412
      ]
    ],
    "S38": [
      [
        "PAT_0093",
        0,
        3733.1002
      ]
    ],
    "S37": [
      [
        "PAT_0068",
        0,
        0.0
      ],
      [
        "PAT_0068",
        0,
        2442.2412
      ]
    ],
    "S22": [
      [
        "PAT_0212",
        0,
        0.0
      ]
    ],
    "S41": [
      [
        "PAT_0107",
        0,
        824.6544
      ],
      [
        "PAT_0152",
        1,
        3266.8956
      ]
    ],
    "S2": [
      [
        "PAT_0034",
        0,
        0.0
      ]
    ],
    "S33": [
      [
        "PAT_0159",
        0,
        0.0
      ],
      [
        "PAT_0159",
        0,
        1973.2855
      ],
      [
        "PAT_0159",
        0,
        3946.571
      ]
    ],
    "S29": [
      [
        "PAT_0171",
        0,
        1369.0581
      ],
      [
        "PAT_0171",
        0,
        3342.3436
      ]
    ],
    "S11": [
      [
        "PAT_0150",
        0,
        2126.7071
      ],
      [
        "PAT_0150",
        0,
        4099.9926
      ]
    ],
    "S31": [
      [
        "PAT_0150",
        0,
        2765.3762
      ],
      [
        "PAT_0150",
        0,
        4738.661700000001
      ]
    ],
    "S23": [
      [
        "PAT_0150",
        0,
        0.0
      ]
    ],
    "S15": [
      [
        "PAT_0013",
        0,
        0.0
      ]
    ],
    "S21": [
      [
        "PAT_0013",
        0,
        0.0
      ]
    ],
    "S36": [
      [
        "PAT_0013",
        0,
        2356.1697
      ]
    ],
    "S3": [
      [
        "PAT_0013",
        0,
        1315.8822
      ]
    ],
    "S40": [
      [
        "PAT_0013",
        0,
        1245.9883
      ]
    ],
    "S18": [
      [
        "PAT_0205",
        0,
        0.0
      ]
    ],
    "S1": [
      [
        "PAT_0207",
        0,
        0.0
      ]
    ],
    "S26": [
      [
        "PAT_0207",
        0,
        0.0
      ]
    ],
    "S28": [
      [
        "PAT_0207",
        0,
        0.0
      ]
    ],
    "S9": [
      [
        "PAT_0232",
        0,
        0.0
      ]
    ],
    "S19": [
      [
        "PAT_0218",
        0,
        0.0
      ]
    ],
    "S5": [
      [
        "PAT_0203",
        0,
        0.0
      ]
    ],
    "S14": [
      [
        "PAT_0232",
        0,
        1543.6783
      ]
    ],
    "S43": [
      [
        "PAT_0204",
        0,
        0.0
      ]
    ],
    "S13": [
      [
        "PAT_0228",
        0,
        0.0
      ]
    ]
  }
}